LICENSE
README.md
pyproject.toml
setup.py
src/aws_maintenance_window_reporter/__init__.py
src/aws_maintenance_window_reporter/__main__.py
src/aws_maintenance_window_reporter/aws_maintenance_window.py
src/aws_maintenance_window_reporter/ec2.py
src/aws_maintenance_window_reporter/environment_parameter.py
src/aws_maintenance_window_reporter/logger.py
src/aws_maintenance_window_reporter/maintenance_action.py
src/aws_maintenance_window_reporter/opensearch.py
src/aws_maintenance_window_reporter/rds.py
src/aws_maintenance_window_reporter/redshift.py
src/aws_maintenance_window_reporter/report.py
src/aws_maintenance_window_reporter.egg-info/PKG-INFO
src/aws_maintenance_window_reporter.egg-info/SOURCES.txt
src/aws_maintenance_window_reporter.egg-info/dependency_links.txt
src/aws_maintenance_window_reporter.egg-info/entry_points.txt
src/aws_maintenance_window_reporter.egg-info/not-zip-safe
src/aws_maintenance_window_reporter.egg-info/requires.txt
src/aws_maintenance_window_reporter.egg-info/top_level.txt