Metadata-Version: 2.1
Name: aws-maintenance-window-reporter
Version: 0.2.5
Summary: Reports AWS maintenance windows
Home-page: https://github.com/binxio/aws-maintenance-window-reporter
Author: Mathijs van Mourick
Author-email: mathijsvanmourick@binx.io
License: BSD
Platform: any
Classifier: Development Status :: 4 - Beta
Classifier: Environment :: Console
Classifier: Intended Audience :: Developers
Classifier: License :: OSI Approved :: BSD License
Classifier: Operating System :: POSIX
Classifier: Operating System :: MacOS
Classifier: Operating System :: Unix
Classifier: Operating System :: Microsoft :: Windows
Classifier: Programming Language :: Python
Classifier: Programming Language :: Python :: 3
Classifier: Topic :: Software Development :: Libraries :: Python Modules
License-File: LICENSE
